rake_spacy/__init__.py
rake_spacy/__version__.py
rake_spacy/aggregators.py
rake_spacy/cog.py
rake_spacy/mappers.py
rake_spacy/phrasers.py
rake_spacy/rake.py
rake_spacy/scorers.py
rake_spacy/stop_tokens.py
rake_spacy-0.3.1.dist-info/LICENSE
rake_spacy-0.3.1.dist-info/WHEEL
rake_spacy-0.3.1.dist-info/METADATA
rake_spacy-0.3.1.dist-info/RECORD
