Metadata-Version: 2.1
Name: rake-spacy
Version: 0.3.1
Summary: Extract keywords/keyphrases from text using the RAKE algorithm.
Home-page: https://github.com/andrewrosss/rake-spacy
License: MIT
Keywords: ml,nlp,rake
Author: Andrew Ross
Author-email: andrew.ross.mail@gmail.com
Requires-Python: >=3.7,<4.0
Classifier: Development Status :: 4 - Beta
Classifier: License :: OSI Approved :: MIT License
Classifier: Programming Language :: Python :: 3
Classifier: Programming Language :: Python :: 3.0
Classifier: Programming Language :: Python :: 3.7
Classifier: Programming Language :: Python :: 3.8
Classifier: Topic :: Scientific/Engineering :: Artificial Intelligence
Requires-Dist: spacy (>=2.2,<4.0)
Project-URL: Documentation, https://github.com/andrewrosss/rake-spacy
Project-URL: Repository, https://github.com/andrewrosss/rake-spacy
